elog/__init__.py
elog/logger.py
n0elog-1.0.0.dist-info/licenses/LICENSE
n0elog-1.0.0.dist-info/METADATA
n0elog-1.0.0.dist-info/WHEEL
n0elog-1.0.0.dist-info/top_level.txt
n0elog-1.0.0.dist-info/RECORD
