Metadata-Version: 2.4
Name: n0elog
Version: 1.0.0
Summary: elog hilft dir besser und Simpler und einfacher alles zu loggen.
Home-page: https://github.com/n0byte/elog
Author: n0byte
Author-email: n0byte@proton.me
Classifier: Programming Language :: Python :: 3
Classifier: License :: OSI Approved :: MIT License
Classifier: Operating System :: OS Independent
Requires-Python: >=3.6
License-File: LICENSE
Dynamic: author
Dynamic: author-email
Dynamic: classifier
Dynamic: description
Dynamic: description-content-type
Dynamic: home-page
Dynamic: license-file
Dynamic: requires-python
Dynamic: summary
